progress-keeper/__init__.py
progress_keeper/__init__.py
progress_keeper-0.1.5.dist-info/LICENSE
progress_keeper-0.1.5.dist-info/METADATA
progress_keeper-0.1.5.dist-info/WHEEL
progress_keeper-0.1.5.dist-info/top_level.txt
progress_keeper-0.1.5.dist-info/RECORD
