Metadata-Version: 2.1
Name: progress-keeper
Version: 0.1.5
Summary: Stores progress in a file, useful for idempotent multi-step processes.
Home-page: https://github.com/AndoKalrisian/progress-keeper
Author: Anders Bergman
Author-email: 
License: MIT License
Platform: UNKNOWN
Classifier: Programming Language :: Python :: 3
Classifier: License :: OSI Approved :: MIT License
Classifier: Operating System :: OS Independent
Requires-Python: >=3.6
Requires-Dist: configparser
